Dotua/__init__.py
Dotua/autodiff.py
Dotua/node.py
Dotua/operator.py
Dotua/rautodiff.py
Dotua/roperator.py
Dotua/rscalar.py
Dotua/scalar.py
Dotua/vector.py
Dotua/nodes/__init__.py
Dotua/nodes/node.py
Dotua/nodes/rscalar.py
Dotua/nodes/rvector.py
Dotua/nodes/scalar.py
Dotua/nodes/vector.py
Dotua/tests/__init__.py
Dotua/tests/test_initializer.py
Dotua/tests/test_operator.py
Dotua/tests/test_rautodiff.py
Dotua/tests/test_roperator.py
Dotua/tests/test_rscalar.py
Dotua/tests/test_rvector.py
Dotua/tests/test_scalar.py
Dotua/tests/test_vector.py
examples/__init__.py
examples/neural_network_demo.py
examples/newton_demo.py
examples/reverse_mode_example.py
Dotua-1.0.0.dist-info/LICENSE
Dotua-1.0.0.dist-info/METADATA
Dotua-1.0.0.dist-info/WHEEL
Dotua-1.0.0.dist-info/top_level.txt
Dotua-1.0.0.dist-info/RECORD
