Metadata-Version: 2.1
Name: Dotua
Version: 1.0.0
Summary: Package for Forward/Reverse Autodifferentiation
Home-page: https://github.com/VV-NS-CY-ZW-CS-207-Organization/cs207-FinalProject
Author: Nick Stern, Vincent Viego, Summer Yuan, Zach Wehrwein
License: MIT
Platform: UNKNOWN
Classifier: Development Status :: 5 - Production/Stable
Classifier: Programming Language :: Python :: 3
Classifier: License :: OSI Approved :: MIT License
Classifier: Operating System :: OS Independent
Requires-Dist: numpy
Requires-Dist: scipy
